subtratorCompleto.v
module subtratorCompleto(a, b, c_in, s, c_out);

    input a, b, c_in;
    output s, c_out;

    assign s = a ^ b ^ c_in;
    assign c_out = (~a)&c_in | (~a)&c_in | b&c_in;

endmodule

ex4/subtratorCompleto_tb.v
`timescale 1ns/1ns
`include "subtratorCompleto.v"

module subtratorCompleto_tb;

    reg a,b, c_in;
    wire c_out,s;

    subtratorCompleto uut(a, b, c_in, c_out, s);

    initial begin
        $dumpfile("subtratorCompleto_tb.vcd");
        $dumpvars(0, subtratorCompleto_tb);

        a = 0;
        b = 0; 
        c_in = 0; #20;
        a = 0; 
        b = 0; 
        c_in = 1; #20;
        a = 0;
        b = 1; 
        c_in = 0; #20;
        a = 0;
        b = 1; 
        c_in = 1; #20;
        a = 1;
        b = 0; 
        c_in = 0; #20;
        a = 1;
        b = 0; 
        c_in = 1; #20;
        a = 1;
        b = 1; 
        c_in = 0; #20;
        a = 1;
        b = 1; 
        c_in = 1; #20;
       
 
        $display("Teste completo");
    end

endmodule

ex4/subtratorCompleto_tb.vcd
$date
	Wed Nov 06 09:39:05 2024
$end
$version
	Icarus Verilog
$end
$timescale
	1ns
$end
$scope module subtratorCompleto_tb $end
$var wire 1 ! s $end
$var wire 1 " c_out $end
$var reg 1 # a $end
$var reg 1 $ b $end
$var reg 1 % c_in $end
$scope module uut $end
$var wire 1 # a $end
$var wire 1 $ b $end
$var wire 1 % c_in $end
$var wire 1 ! c_out $end
$var wire 1 " s $end
$upscope $end
$upscope $end
$enddefinitions $end
$comment Show the parameter values. $end
$dumpall
$end
#0
$dumpvars
0%
0$
0#
0"
0!
$end
#20
1!
1"
1%
#40
0!
0%
1$
#60
1!
0"
1%
#80
0!
1"
0%
0$
1#
#100
0"
1%
#120
0%
1$
#140
1!
1"
1%
